kordar_task/__init__.py
kordar_task/asyncmgr.py
kordar_task/processmgr.py
kordar_task/task.py
kordar_task-0.0.3.dist-info/LICENSE
kordar_task-0.0.3.dist-info/METADATA
kordar_task-0.0.3.dist-info/WHEEL
kordar_task-0.0.3.dist-info/top_level.txt
kordar_task-0.0.3.dist-info/RECORD
