Metadata-Version: 2.1
Name: kordar-task
Version: 0.0.3
Summary: 基于多进程、异步IO的任务处理器
Author: Kordar
Author-email: 572821520@qq.com
Classifier: Programming Language :: Python :: 3
Classifier: License :: OSI Approved :: MIT License
Classifier: Operating System :: OS Independent
License-File: LICENSE
